bareasgi_sspi/__init__.py
bareasgi_sspi/constants.py
bareasgi_sspi/helpers.py
bareasgi_sspi/py.typed
bareasgi_sspi/session_manager.py
bareasgi_sspi/spnego_middleware.py
bareasgi_sspi-4.2.0.dist-info/LICENSE
bareasgi_sspi-4.2.0.dist-info/WHEEL
bareasgi_sspi-4.2.0.dist-info/METADATA
bareasgi_sspi-4.2.0.dist-info/RECORD
