Metadata-Version: 2.1
Name: bareasgi-sspi
Version: 4.2.0
Summary: bareASGI middleware for SSPI
Home-page: https://github.com/rob-blackbourn/bareASGI-SSPI
License: Apache-2.0
Author: Rob Blackbourn
Author-email: rob.blackbourn@gmail.com
Requires-Python: >=3.8,<4.0
Classifier: Development Status :: 3 - Alpha
Classifier: Environment :: Web Environment
Classifier: Environment :: Win32 (MS Windows)
Classifier: Framework :: AsyncIO
Classifier: Intended Audience :: Developers
Classifier: License :: OSI Approved :: Apache Software License
Classifier: Operating System :: Microsoft :: Windows
Classifier: Programming Language :: Python :: 3
Classifier: Programming Language :: Python :: 3.10
Classifier: Programming Language :: Python :: 3.8
Classifier: Programming Language :: Python :: 3.9
Classifier: Topic :: Internet :: WWW/HTTP
Classifier: Topic :: Security
Classifier: Typing :: Typed
Requires-Dist: bareasgi (>=4.2,<5.0)
Requires-Dist: pyspnego (>=0.6,<0.7)
Project-URL: Repository, https://github.com/rob-blackbourn/bareASGI-SSPI
